README.rst
retrying_async.py
setup.py
retrying_async.egg-info/PKG-INFO
retrying_async.egg-info/SOURCES.txt
retrying_async.egg-info/dependency_links.txt
retrying_async.egg-info/not-zip-safe
retrying_async.egg-info/requires.txt
retrying_async.egg-info/top_level.txt