Metadata-Version: 1.1
Name: retrying-async
Version: 1.1.0
Summary: Simple retrying for asyncio
Home-page: https://github.com/lxl0928/retrying_async
Author: OCEAN S.A. & Timi.long
Author-email: lixiaolong@smuer.cn
License: UNKNOWN
Keywords: asyncio,retrying
Platform: UNKNOWN
Classifier: Development Status :: 4 - Beta
Classifier: Intended Audience :: Developers
Classifier: License :: OSI Approved :: MIT License
Classifier: Programming Language :: Python
Classifier: Programming Language :: Python :: 3
Classifier: Programming Language :: Python :: 3.5
Classifier: Programming Language :: Python :: 3.6
Classifier: Programming Language :: Python :: 3.7
